chirality/__init__.py
chirality/normative_spec.txt
chirality/application/__init__.py
chirality/application/lenses/__init__.py
chirality/application/lenses/catalog_generator.py
chirality/application/lenses/catalog_manager.py
chirality/application/lenses/lens_resolver.py
chirality/application/lenses/overrides_manager.py
chirality/application/phase1/__init__.py
chirality/application/phase1/aggregator.py
chirality/application/phase1/contracts.py
chirality/application/phase1/dialogue_run.py
chirality/application/phase1/dialogue_run_updates.py
chirality/application/phase1/snapshotter.py
chirality/application/phase2/__init__.py
chirality/application/phase2/tensor_engine.py
chirality/application/services/__init__.py
chirality/application/services/cell_computation_service.py
chirality/domain/__init__.py
chirality/domain/budgets.py
chirality/domain/constants.py
chirality/domain/contracts.py
chirality/domain/preflight.py
chirality/domain/pricing.py
chirality/domain/provenance.py
chirality/domain/stations.py
chirality/domain/types.py
chirality/domain/validation.py
chirality/domain/matrices/__init__.py
chirality/domain/matrices/canonical.py
chirality/domain/pipeline/__init__.py
chirality/domain/pipeline/stages.py
chirality/domain/semantics/__init__.py
chirality/domain/semantics/lens.py
chirality/domain/semantics/lens_catalog.py
chirality/domain/semantics/operations.py
chirality/infrastructure/__init__.py
chirality/infrastructure/caching.py
chirality/infrastructure/api/guards.py
chirality/infrastructure/export/__init__.py
chirality/infrastructure/export/neo4j_loader.py
chirality/infrastructure/lenses/__init__.py
chirality/infrastructure/lenses/build.py
chirality/infrastructure/lenses/derive.py
chirality/infrastructure/llm/__init__.py
chirality/infrastructure/llm/budget_resolver.py
chirality/infrastructure/llm/config.py
chirality/infrastructure/llm/mock_resolvers.py
chirality/infrastructure/llm/openai_adapter.py
chirality/infrastructure/llm/repair.py
chirality_framework-19.4.0.dist-info/licenses/LICENSE
chirality_framework-19.4.0.dist-info/METADATA
chirality_framework-19.4.0.dist-info/WHEEL
chirality_framework-19.4.0.dist-info/entry_points.txt
chirality_framework-19.4.0.dist-info/top_level.txt
chirality_framework-19.4.0.dist-info/RECORD
