Metadata-Version: 2.4
Name: chirality-framework
Version: 19.4.0
Summary: A semantic calculator for executing a canonical, multi-stage pipeline for structured problem-solving and knowledge generation.
Author: Chirality Framework Team
Maintainer: Chirality Framework Team
License-Expression: MIT
Project-URL: Homepage, https://github.com/sgttomas/chirality-framework
Project-URL: Repository, https://github.com/sgttomas/chirality-framework.git
Project-URL: Issues, https://github.com/sgttomas/chirality-framework/issues
Project-URL: Documentation, https://github.com/sgttomas/chirality-framework/blob/main/README.md
Keywords: llm,ontology,semantic computing,pipeline orchestration,static site generator,knowledge generation
Classifier: Development Status :: 4 - Beta
Classifier: Intended Audience :: Developers
Classifier: Intended Audience :: Science/Research
Classifier: Topic :: Software Development :: Libraries :: Python Modules
Classifier: Topic :: Scientific/Engineering :: Artificial Intelligence
Classifier: Programming Language :: Python :: 3
Classifier: Programming Language :: Python :: 3.9
Classifier: Programming Language :: Python :: 3.10
Classifier: Programming Language :: Python :: 3.11
Classifier: Programming Language :: Python :: 3.12
Classifier: Programming Language :: Python :: 3.13
Requires-Python: >=3.9
License-File: LICENSE
Requires-Dist: click>=8.0.0
Requires-Dist: python-dotenv>=1.0.0
Requires-Dist: PyYAML>=6.0
Requires-Dist: pydantic>=2.0.0
Provides-Extra: openai
Requires-Dist: openai>=1.50.0; extra == "openai"
Provides-Extra: neo4j
Requires-Dist: neo4j>=5.0.0; extra == "neo4j"
Provides-Extra: dev
Requires-Dist: pytest>=7.0.0; extra == "dev"
Requires-Dist: pytest-cov>=4.0.0; extra == "dev"
Requires-Dist: black>=22.0.0; extra == "dev"
Requires-Dist: mypy>=1.0.0; extra == "dev"
Requires-Dist: ruff>=0.4.0; extra == "dev"
Provides-Extra: all
Requires-Dist: openai>=1.42.0; extra == "all"
Requires-Dist: neo4j>=5.0.0; extra == "all"
Dynamic: license-file
